src/Dialog.py
src/__init__.py
PyTkDialoggg-0.0.1.dist-info/METADATA
PyTkDialoggg-0.0.1.dist-info/WHEEL
PyTkDialoggg-0.0.1.dist-info/top_level.txt
PyTkDialoggg-0.0.1.dist-info/RECORD
