Metadata-Version: 2.1
Name: PyTkDialoggg
Version: 0.0.1
Summary: Module for Dialog
Home-page: https://github.com/lawbreakerr/Dialog
Author: Arman Ahmadi
Author-email: armanagha6@gmail.com
License: UNKNOWN
Platform: UNKNOWN
Classifier: Programming Language :: Python :: 3
Classifier: License :: OSI Approved :: MIT License
Classifier: Operating System :: OS Independent
Requires-Python: >=3.6
